hirakanadic/cli.py
hirakanadic-0.0.4.dist-info/METADATA
hirakanadic-0.0.4.dist-info/WHEEL
hirakanadic-0.0.4.dist-info/entry_points.txt
hirakanadic-0.0.4.dist-info/RECORD
