Metadata-Version: 2.1
Name: hirakanadic
Version: 0.0.4
Summary: 
Home-page: http://github.com/po3rin/hirakanadic
License: Apache-2.0
Author: po3rin
Requires-Python: >=3.11,<4.0
Classifier: License :: OSI Approved :: Apache Software License
Classifier: Programming Language :: Python :: 3
Classifier: Programming Language :: Python :: 3.11
Requires-Dist: jaconv (>=0.2.4,<0.3.0)
Requires-Dist: sudachidict-core (>=20230110,<20230111)
Requires-Dist: sudachidict-full (>=20230110,<20230111)
Requires-Dist: sudachipy (>=0.6.7,<0.7.0)
Project-URL: Repository, http://github.com/po3rin/hirakanadic
